Metadata-Version: 2.1
Name: nushell
Version: 0.0.16
Summary: Python module to easily create nushell plugins
Home-page: http://www.github.com/vsoch/nushell-plugin-python
Author: Vanessa Sochat
Author-email: vsochat@stanford.edu
Maintainer: Vanessa Sochat
Maintainer-email: vsochat@stanford.edu
License: LICENSE
Keywords: nushell,plugin,nu
Platform: UNKNOWN
Classifier: Intended Audience :: Science/Research
Classifier: Intended Audience :: Developers
Classifier: Programming Language :: Python
Classifier: Topic :: Software Development
Classifier: Topic :: Scientific/Engineering
Classifier: Operating System :: Unix
Classifier: Programming Language :: Python :: 3
